EQTransformer/__init__.py
EQTransformer/core/EqT_utils.py
EQTransformer/core/__init__.py
EQTransformer/core/mseed_predictor.py
EQTransformer/core/predictor.py
EQTransformer/core/tester.py
EQTransformer/core/trainer.py
EQTransformer/utils/__init__.py
EQTransformer/utils/associator.py
EQTransformer/utils/downloader.py
EQTransformer/utils/hdf5_maker.py
EQTransformer/utils/plot.py
tests/__init__.py
tests/test_downloader.py
tests/test_hdf5maker.py
tests/test_predictor.py
tests/test_tester.py
tests/test_trainer.py
EQTransformer-0.1.59.dist-info/LICENSE
EQTransformer-0.1.59.dist-info/METADATA
EQTransformer-0.1.59.dist-info/WHEEL
EQTransformer-0.1.59.dist-info/top_level.txt
EQTransformer-0.1.59.dist-info/RECORD
