Metadata-Version: 2.1
Name: EQTransformer
Version: 0.1.59
Summary: A python package for making and using attentive deep-learning models for earthquake signal detection and phase picking.
Home-page: https://github.com/smousavi05/EQTransformer
Author: S. Mostafa Mousavi
Author-email: smousavi05@gmail.com
License: MIT
Keywords: Seismology,Earthquakes Detection,P&S Picking,Deep Learning,Attention Mechanism
Platform: UNKNOWN
Requires-Python: >=3.6
Requires-Dist: pytest
Requires-Dist: keyring (>=15.1)
Requires-Dist: pkginfo (>=1.4.2)
Requires-Dist: scipy (==1.4.1)
Requires-Dist: tensorflow (==2.0.0)
Requires-Dist: keras (==2.3.1)
Requires-Dist: matplotlib
Requires-Dist: pandas
Requires-Dist: tqdm (==4.48.0)
Requires-Dist: h5py (==2.10.0)
Requires-Dist: obspy
Requires-Dist: jupyter
